yay/__init__.py
yay/configuration.py
yay/exceptions.py
yayconf-0.1.0b2.dist-info/LICENSE
yayconf-0.1.0b2.dist-info/METADATA
yayconf-0.1.0b2.dist-info/WHEEL
yayconf-0.1.0b2.dist-info/top_level.txt
yayconf-0.1.0b2.dist-info/RECORD
